{"is_source_file": true, "format": "md", "description": ".md file: README.md", "external_files": [], "external_methods": [], "published": [], "classes": [], "methods": [], "calls": [], "search-terms": ["README.md", "md"], "state": 2, "filename": "README.md", "format-version": 4, "code-base-name": "https://github.com/kavia-common/react-tic-tac-toe-221744-221753.git:kavia-main", "knowledge_revision": 3, "git_revision": "c07e790ff88625c21302cad0a15815cbcb5ffae1", "revision_history": [{"3": "c07e790ff88625c21302cad0a15815cbcb5ffae1"}]}